pltrdy/__init__.py
pltrdy/assertion.py
pltrdy/cmd.py
pltrdy/describe.py
pltrdy/explore_results.py
pltrdy/gen_script.py
pltrdy/git.py
pltrdy/percentiles.py
pltrdy/pickle.py
pltrdy/quiet.py
pltrdy/reload.py
pltrdy/rouge.py
pltrdy/stats.py
pltrdy/tee.py
pltrdy/test_gen_script.py
pltrdy/time.py
pltrdy/tmpdir.py
pltrdy/types.py
pltrdy/wc.py
pltrdy-0.3.12.dist-info/METADATA
pltrdy-0.3.12.dist-info/WHEEL
pltrdy-0.3.12.dist-info/entry_points.txt
pltrdy-0.3.12.dist-info/top_level.txt
pltrdy-0.3.12.dist-info/RECORD
