Metadata-Version: 2.1
Name: pltrdy
Version: 0.3.12
Requires-Dist: pytz
